setup.py
dnds_cal/__init__.py
dnds_cal/aa.py
dnds_cal/dnds.py
dnds_cal/test.py
dnds_cal.egg-info/PKG-INFO
dnds_cal.egg-info/SOURCES.txt
dnds_cal.egg-info/dependency_links.txt
dnds_cal.egg-info/top_level.txt