Metadata-Version: 1.2
Name: dnds-cal
Version: 0.0.2
Summary: Calculate the dn/ds (also pn and ps) value of cds
Home-page: https://github.com/zhutao1009/dnds
Author: Zhu Tao
Author-email: zhutao@cau.edu.cn
License: UNKNOWN
Platform: UNKNOWN
Classifier: Programming Language :: Python :: 3
Classifier: License :: OSI Approved :: MIT License
Classifier: Operating System :: OS Independent
Requires-Python: >=3.0
